setup.py
pytosca/__init__.py
pytosca/tosca.py
pytosca/tosca_schema.yaml
pytosca.egg-info/PKG-INFO
pytosca.egg-info/SOURCES.txt
pytosca.egg-info/dependency_links.txt
pytosca.egg-info/requires.txt
pytosca.egg-info/top_level.txt
pytosca/tests/__init__.py
pytosca/tests/test_tosca.py
pytosca/tests/data/__init__.py