Metadata-Version: 1.1
Name: pytosca
Version: 0.2.1
Summary: Application topologies using OASIS TOSCA YAML Profile
Home-page: https://github.com/kapilt/pytosca
Author: Kapil Thangavelu
Author-email: kapil.foss@gmail.com
License: Apache
Platform: UNKNOWN
Classifier: Intended Audience :: Developers
Classifier: Programming Language :: Python
Classifier: License :: OSI Approved :: Apache Software License
Classifier: Operating System :: OS Independent
